clyde/__init__.py
clyde/component.py
clyde/embed.py
clyde/markdown.py
clyde/poll.py
clyde/py.typed
clyde/timestamp.py
clyde/validation.py
clyde/webhook.py
clyde/components/__init__.py
clyde/components/action_row.py
clyde/components/button.py
clyde/components/container.py
clyde/components/file.py
clyde/components/media_gallery.py
clyde/components/section.py
clyde/components/seperator.py
clyde/components/text_display.py
clyde/components/thumbnail.py
clyde/components/unfurled_media_item.py
discord_clyde-0.3.0.dist-info/METADATA
discord_clyde-0.3.0.dist-info/WHEEL
discord_clyde-0.3.0.dist-info/licenses/LICENSE
discord_clyde-0.3.0.dist-info/RECORD
