Metadata-Version: 2.4
Name: discord-clyde
Version: 0.3.0
Summary: A modern, type-hinted Python library for seamless interaction with the Discord Webhook API.
Project-URL: Repository, https://github.com/EthanC/Clyde
Project-URL: Issues, https://github.com/EthanC/Clyde/issues
Project-URL: Changelog, https://github.com/EthanC/Clyde/releases
Author-email: Ethan C <16727756+EthanC@users.noreply.github.com>
License-Expression: AGPL-3.0
License-File: LICENSE
Keywords: api,discord,library,rest,webhook,wrapper
Classifier: Development Status :: 3 - Alpha
Classifier: Intended Audience :: Developers
Classifier: Programming Language :: Python :: 3.13
Requires-Python: >=3.13
Requires-Dist: httpx>=0.28.1
Requires-Dist: msgspec>=0.19.0
